quake_sdk/__init__.py
quake_sdk/client.py
quake_sdk/exceptions.py
quake_sdk/models.py
quake_sdk/type_guards.py
quake_sdk/utils.py
quake_sdk-0.3.2.dist-info/METADATA
quake_sdk-0.3.2.dist-info/WHEEL
quake_sdk-0.3.2.dist-info/RECORD
