Metadata-Version: 2.3
Name: quake-sdk
Version: 0.3.2
Summary: 
Author: John Doe
Author-email: johndoe@example.com
Requires-Python: >=3.11
Classifier: Programming Language :: Python :: 3
Classifier: Programming Language :: Python :: 3.11
Classifier: Programming Language :: Python :: 3.12
Classifier: Programming Language :: Python :: 3.13
Requires-Dist: pydantic (>=2.7.0,<3.0.0)
Requires-Dist: pyrate-limiter (>=3.7.0,<4.0.0) ; python_version >= "3.11" and python_version < "4.0"
Requires-Dist: requests (>=2.31.0,<3.0.0)
